{
  "name": "Daytona AI Content Editor",
  "image": "mcr.microsoft.com/devcontainers/javascript-node:20",
  "settings": {
    "terminal.integrated.defaultProfile.linux": "bash"
  },
  "extensions": [
    "dbaeumer.vscode-eslint",
    "esbenp.prettier-vscode"
  ],
  "features": {
    "ghcr.io/devcontainers/features/node:1": {
      "version": "20"
    },
    "ghcr.io/devcontainers/features/git:1": {}
  },
  "postCreateCommand": "npm install",
  "ports": [
    "3000:3000"
  ],
  "workspaceFolder": "/workspace",
  "remoteUser": "node"
}